{
    "packages": {
        "devenv-runtimes": "v4.0.1",
        "devenv-github-workflows": "v6.0.2",
        "devenv-github-templates": "v1.0.5",
        "devenv-devcontainer-setup": "v2.4.0"
    },
    "components": [
        "devcontainer-setup",
        "runtime-local",
        "vehicle-signal-interface",
        "build-system",
        "conan-setup",
        "sdk-installer"
    ],
    "variables": {
        "language": "cpp",
        "repoType": "app",
        "appManifestPath": "app/AppManifest.json",
        "githubRepoId": "eclipse-velocitas/vehicle-app-cpp-template",
        "vehicleAppPort": -1,
        "mockFilePath": "mock.py"
    },
    "cliVersion": "v0.9.1"
}
